livecodec/__init__.py
livecodec/codec.py
livecodec/evit.py
livecodec/monarch.py
livecodec-0.0.1.dist-info/METADATA
livecodec-0.0.1.dist-info/WHEEL
livecodec-0.0.1.dist-info/top_level.txt
livecodec-0.0.1.dist-info/RECORD
